known_pose_client/__init__.py
known_pose_client/api_client.py
known_pose_client/configuration.py
known_pose_client/exceptions.py
known_pose_client/rest.py
known_pose_client/api/__init__.py
known_pose_client/api/developers_api.py
known_pose_client/models/__init__.py
known_pose_client/models/accurate_pose.py
known_pose_client/models/basic_pose.py
known_pose_client/models/inaccurate_pose.py
known_pose_client/models/inline_response200.py
known_pose_client/models/orientation.py
known_pose_client/models/position.py
known_pose_client-1.1.6.dist-info/METADATA
known_pose_client-1.1.6.dist-info/WHEEL
known_pose_client-1.1.6.dist-info/top_level.txt
known_pose_client-1.1.6.dist-info/RECORD
